showdown/__init__.py
showdown/bulk.py
showdown/game.py
showdown/ui.py
showdown/examples/__init__.py
showdown/examples/copycat.py
showdown/examples/randomizer.py
showdown/examples/shuffler.py
showdown-0.1.0.dev0.dist-info/DESCRIPTION.rst
showdown-0.1.0.dev0.dist-info/METADATA
showdown-0.1.0.dev0.dist-info/RECORD
showdown-0.1.0.dev0.dist-info/WHEEL
showdown-0.1.0.dev0.dist-info/entry_points.txt
showdown-0.1.0.dev0.dist-info/metadata.json
showdown-0.1.0.dev0.dist-info/top_level.txt
showdown-0.1.0.dev0.dist-info/zip-safe
