Metadata-Version: 2.0
Name: showdown
Version: 0.1.0.dev0
Summary: "This town is not big enough for both of our bots"
Home-page: https://github.com/ewjoachim/showdown
Author: Joachim Jablon
Author-email: ewjoachim@gmail.com
License: Apache Software License
Keywords: game,bots,ia
Platform: UNKNOWN
Classifier: Development Status :: 4 - Beta
Classifier: Intended Audience :: Developers
Classifier: License :: OSI Approved :: Apache Software License
Classifier: Natural Language :: English
Classifier: Programming Language :: Python :: 3.6
Provides-Extra: dev
Provides-Extra: lint
Requires-Dist: prospector[with_pyroma]; extra == 'lint'
Requires-Dist: pyroma (==2.0); extra == 'lint'
Provides-Extra: test
Requires-Dist: pytest; extra == 'test'
